barbar/Bar.py
barbar/Barbar.py
barbar/__init__.py
barbar-0.2.1.dist-info/DESCRIPTION.rst
barbar-0.2.1.dist-info/METADATA
barbar-0.2.1.dist-info/RECORD
barbar-0.2.1.dist-info/WHEEL
barbar-0.2.1.dist-info/metadata.json
barbar-0.2.1.dist-info/top_level.txt
