Metadata-Version: 2.0
Name: barbar
Version: 0.2.1
Summary: Progress bar for deep learning training iterations
Home-page: https://github.com/yusugomori/barbar
Author: Yusuke Sugomori
Author-email: me@yusugomori.com
License: MIT
Keywords: deep learning pytorch tensorflow keras
Platform: UNKNOWN
Classifier: Development Status :: 3 - Alpha
Classifier: Intended Audience :: Developers
Classifier: Intended Audience :: Education
Classifier: Intended Audience :: Science/Research
Classifier: Programming Language :: Python :: 3
Classifier: Topic :: Scientific/Engineering
Classifier: Topic :: Scientific/Engineering :: Mathematics
Classifier: Topic :: Scientific/Engineering :: Artificial Intelligence
Classifier: Topic :: Software Development
Classifier: Topic :: Software Development :: Libraries
Classifier: Topic :: Software Development :: Libraries :: Python Modules
